roman_numerals_webservice/__init__.py
roman_numerals_webservice/cli.py
roman_numerals_webservice/roman_numerals_webservice.py
roman_numerals_webservice/roman_numerals/__init__.py
roman_numerals_webservice/roman_numerals/arabic_to_roman.py
roman_numerals_webservice/roman_numerals/roman_to_arabic.py
roman_numerals_webservice-0.4.1.dist-info/AUTHORS.rst
roman_numerals_webservice-0.4.1.dist-info/LICENSE
roman_numerals_webservice-0.4.1.dist-info/METADATA
roman_numerals_webservice-0.4.1.dist-info/WHEEL
roman_numerals_webservice-0.4.1.dist-info/entry_points.txt
roman_numerals_webservice-0.4.1.dist-info/top_level.txt
roman_numerals_webservice-0.4.1.dist-info/RECORD
