Metadata-Version: 2.1
Name: roman-numerals-webservice
Version: 0.4.1
Summary: A python package for a minimalist webservice to convert roman numerals to araic numerals and vice versa.
Home-page: https://github.com/DerThorsten/roman_numerals_webservice
Author: Thorsten Beier
Author-email: derthorstenbeier@gmail.com
License: MIT license
Keywords: roman_numerals_webservice
Platform: UNKNOWN
Classifier: Development Status :: 2 - Pre-Alpha
Classifier: Intended Audience :: Developers
Classifier: License :: OSI Approved :: MIT License
Classifier: Natural Language :: English
Classifier: Programming Language :: Python :: 3.6
Classifier: Programming Language :: Python :: 3.7
Requires-Dist: Click (>=6.0)
Requires-Dist: cherrypy (>=18.0.0requests>=2.22.0)
